setup.py
lsr/__init__.py
lsr/speech.py
lsr.egg-info/PKG-INFO
lsr.egg-info/SOURCES.txt
lsr.egg-info/dependency_links.txt
lsr.egg-info/requires.txt
lsr.egg-info/top_level.txt