Metadata-Version: 1.0
Name: lsr
Version: 0.0.1
Summary: api de reconnaissance vocale avec une magnifique voix feminine
Home-page: UNKNOWN
Author: Kilian Barantal
Author-email: kilianbarantal83@gmail.com
License: UNKNOWN
Platform: UNKNOWN
